rabbitair/__init__.py
rabbitair/client.py
rabbitair/exceptions.py
rabbitair/py.typed
rabbitair/response.py
rabbitair/tcp.py
rabbitair/udp.py
python_rabbitair-0.0.8.dist-info/LICENSE
python_rabbitair-0.0.8.dist-info/METADATA
python_rabbitair-0.0.8.dist-info/WHEEL
python_rabbitair-0.0.8.dist-info/top_level.txt
python_rabbitair-0.0.8.dist-info/RECORD
