Metadata-Version: 2.1
Name: python-rabbitair
Version: 0.0.8
Summary: Python library for local control of Rabbit Air air purifiers
Home-page: https://github.com/rabbit-air/python-rabbitair
Author: Rabbit Air
Author-email: developer@rabbitair.com
License: Apache-2.0
Project-URL: Bug Tracker, https://github.com/rabbit-air/python-rabbitair/issues
Platform: any
Classifier: Development Status :: 4 - Beta
Classifier: Intended Audience :: Developers
Classifier: License :: OSI Approved :: Apache Software License
Classifier: Operating System :: POSIX :: Linux
Classifier: Programming Language :: Python :: 3
Classifier: Topic :: Home Automation
Requires-Python: >=3.7
License-File: LICENSE
